{
"meta":{"test_sets":[],"test_metrics":[],"learn_metrics":[{"best_value":"Min","name":"RMSE"}],"launch_mode":"Train","parameters":"","iteration_count":100,"learn_sets":["learn"],"name":"experiment"},
"iterations":[
{"learn":[14.005006],"iteration":0,"passed_time":0.001081609934,"remaining_time":0.1070793835},
{"learn":[13.14441192],"iteration":1,"passed_time":0.001837283037,"remaining_time":0.09002686881},
{"learn":[12.34258257],"iteration":2,"passed_time":0.002609157264,"remaining_time":0.08436275154},
{"learn":[11.64527793],"iteration":3,"passed_time":0.00346815742,"remaining_time":0.08323577808},
{"learn":[11.02766183],"iteration":4,"passed_time":0.004587580546,"remaining_time":0.08716403036},
{"learn":[10.43485794],"iteration":5,"passed_time":0.005684153356,"remaining_time":0.08905173591},
{"learn":[9.890641275],"iteration":6,"passed_time":0.007222524453,"remaining_time":0.09595639631},
{"learn":[9.492161212],"iteration":7,"passed_time":0.008244006043,"remaining_time":0.0948060695},
{"learn":[9.105082953],"iteration":8,"passed_time":0.009387361107,"remaining_time":0.09491665119},
{"learn":[8.674157135],"iteration":9,"passed_time":0.01032531507,"remaining_time":0.09292783559},
{"learn":[8.341743544],"iteration":10,"passed_time":0.01156464836,"remaining_time":0.09356851853},
{"learn":[8.049372916],"iteration":11,"passed_time":0.0126480543,"remaining_time":0.09275239821},
{"learn":[7.757318612],"iteration":12,"passed_time":0.01359878811,"remaining_time":0.09100727431},
{"learn":[7.522206899],"iteration":13,"passed_time":0.01456117998,"remaining_time":0.08944724847},
{"learn":[7.297756655],"iteration":14,"passed_time":0.01581869089,"remaining_time":0.08963924837},
{"learn":[7.088359431],"iteration":15,"passed_time":0.01684931857,"remaining_time":0.08845892249},
{"learn":[6.882113791],"iteration":16,"passed_time":0.01766698445,"remaining_time":0.0862564535},
{"learn":[6.704728832],"iteration":17,"passed_time":0.01836055241,"remaining_time":0.08364251652},
{"learn":[6.563881962],"iteration":18,"passed_time":0.01965140123,"remaining_time":0.0837770263},
{"learn":[6.418790279],"iteration":19,"passed_time":0.02121915821,"remaining_time":0.08487663284},
{"learn":[6.315756953],"iteration":20,"passed_time":0.02281985794,"remaining_time":0.08584613224},
{"learn":[6.210157751],"iteration":21,"passed_time":0.02385493766,"remaining_time":0.08457659716},
{"learn":[6.115058449],"iteration":22,"passed_time":0.02474517464,"remaining_time":0.08284254118},
{"learn":[6.014819884],"iteration":23,"passed_time":0.02605408212,"remaining_time":0.08250459337},
{"learn":[5.93117229],"iteration":24,"passed_time":0.02767534901,"remaining_time":0.08302604703},
{"learn":[5.844857622],"iteration":25,"passed_time":0.028504301,"remaining_time":0.08112762593},
{"learn":[5.771145213],"iteration":26,"passed_time":0.02921378477,"remaining_time":0.07898541807},
{"learn":[5.704018229],"iteration":27,"passed_time":0.03063082414,"remaining_time":0.07876497637},
{"learn":[5.665806474],"iteration":28,"passed_time":0.03247373847,"remaining_time":0.07950467004},
{"learn":[5.616500369],"iteration":29,"passed_time":0.03402109149,"remaining_time":0.07938254682},
{"learn":[5.558023666],"iteration":30,"passed_time":0.0355732343,"remaining_time":0.07917913441},
{"learn":[5.510080976],"iteration":31,"passed_time":0.03737891202,"remaining_time":0.07943018805},
{"learn":[5.468747792],"iteration":32,"passed_time":0.03896767089,"remaining_time":0.07911618029},
{"learn":[5.429275534],"iteration":33,"passed_time":0.04012708772,"remaining_time":0.07789375851},
{"learn":[5.402117324],"iteration":34,"passed_time":0.04112746478,"remaining_time":0.07637957745},
{"learn":[5.367635151],"iteration":35,"passed_time":0.0420182749,"remaining_time":0.07469915538},
{"learn":[5.345181232],"iteration":36,"passed_time":0.04274908071,"remaining_time":0.07278897526},
{"learn":[5.319151269],"iteration":37,"passed_time":0.04383004719,"remaining_time":0.07151218226},
{"learn":[5.296134146],"iteration":38,"passed_time":0.04461555691,"remaining_time":0.06978330695},
{"learn":[5.269629003],"iteration":39,"passed_time":0.04551905648,"remaining_time":0.06827858472},
{"learn":[5.251147059],"iteration":40,"passed_time":0.04616914324,"remaining_time":0.06643852319},
{"learn":[5.248003302],"iteration":41,"passed_time":0.04644565402,"remaining_time":0.0641392365},
{"learn":[5.232376509],"iteration":42,"passed_time":0.04720738465,"remaining_time":0.06257723082},
{"learn":[5.213524255],"iteration":43,"passed_time":0.04802967521,"remaining_time":0.06112867754},
{"learn":[5.189691584],"iteration":44,"passed_time":0.04877314035,"remaining_time":0.05961161598},
{"learn":[5.166052198],"iteration":45,"passed_time":0.04962022193,"remaining_time":0.05824982574},
{"learn":[5.140406659],"iteration":46,"passed_time":0.05078433531,"remaining_time":0.05726744195},
{"learn":[5.118929684],"iteration":47,"passed_time":0.0514919289,"remaining_time":0.05578292298},
{"learn":[5.108792602],"iteration":48,"passed_time":0.05241724739,"remaining_time":0.05455672688},
{"learn":[5.098141225],"iteration":49,"passed_time":0.05334035241,"remaining_time":0.05334035241},
{"learn":[5.085926393],"iteration":50,"passed_time":0.05416514112,"remaining_time":0.05204101794},
{"learn":[5.067816804],"iteration":51,"passed_time":0.0548872409,"remaining_time":0.05066514545},
{"learn":[5.049834901],"iteration":52,"passed_time":0.05566773233,"remaining_time":0.0493657249},
{"learn":[5.03838627],"iteration":53,"passed_time":0.05648812613,"remaining_time":0.04811951485},
{"learn":[5.033534248],"iteration":54,"passed_time":0.05728511059,"remaining_time":0.04686963594},
{"learn":[5.023726885],"iteration":55,"passed_time":0.05795149452,"remaining_time":0.04553331712},
{"learn":[5.01290392],"iteration":56,"passed_time":0.05865100481,"remaining_time":0.04424549486},
{"learn":[5.005569127],"iteration":57,"passed_time":0.05934799027,"remaining_time":0.04297613088},
{"learn":[4.989969032],"iteration":58,"passed_time":0.06005243347,"remaining_time":0.04173135207},
{"learn":[4.976762446],"iteration":59,"passed_time":0.0608129541,"remaining_time":0.0405419694},
{"learn":[4.967222715],"iteration":60,"passed_time":0.06153472211,"remaining_time":0.03934187151},
{"learn":[4.954407599],"iteration":61,"passed_time":0.06239388925,"remaining_time":0.03824141599},
{"learn":[4.942125056],"iteration":62,"passed_time":0.06319568703,"remaining_time":0.0371149273},
{"learn":[4.930230716],"iteration":63,"passed_time":0.06410353005,"remaining_time":0.03605823565},
{"learn":[4.921695642],"iteration":64,"passed_time":0.06503002526,"remaining_time":0.03501616745},
{"learn":[4.906405625],"iteration":65,"passed_time":0.06579457735,"remaining_time":0.03389417621},
{"learn":[4.894330248],"iteration":66,"passed_time":0.06655839527,"remaining_time":0.03278249319},
{"learn":[4.88211557],"iteration":67,"passed_time":0.06776279583,"remaining_time":0.03188837451},
{"learn":[4.877946398],"iteration":68,"passed_time":0.06854862821,"remaining_time":0.03079720977},
{"learn":[4.863182126],"iteration":69,"passed_time":0.06933225308,"remaining_time":0.02971382275},
{"learn":[4.84646533],"iteration":70,"passed_time":0.07016020129,"remaining_time":0.02865698363},
{"learn":[4.838014752],"iteration":71,"passed_time":0.07132096842,"remaining_time":0.02773593216},
{"learn":[4.82981137],"iteration":72,"passed_time":0.07244752568,"remaining_time":0.02679566018},
{"learn":[4.817094767],"iteration":73,"passed_time":0.07317698495,"remaining_time":0.02571083255},
{"learn":[4.808314151],"iteration":74,"passed_time":0.07381264117,"remaining_time":0.02460421372},
{"learn":[4.796235023],"iteration":75,"passed_time":0.07482977398,"remaining_time":0.02363045494},
{"learn":[4.784434534],"iteration":76,"passed_time":0.07566915457,"remaining_time":0.02260247474},
{"learn":[4.774402487],"iteration":77,"passed_time":0.07629600556,"remaining_time":0.02151938618},
{"learn":[4.76731896],"iteration":78,"passed_time":0.07720537591,"remaining_time":0.02052294803},
{"learn":[4.75934113],"iteration":79,"passed_time":0.07805723723,"remaining_time":0.01951430931},
{"learn":[4.754106378],"iteration":80,"passed_time":0.0793147202,"remaining_time":0.01860468745},
{"learn":[4.744002932],"iteration":81,"passed_time":0.08007099501,"remaining_time":0.01757655988},
{"learn":[4.731700554],"iteration":82,"passed_time":0.08090420318,"remaining_time":0.01657074041},
{"learn":[4.723284153],"iteration":83,"passed_time":0.08162788239,"remaining_time":0.01554816807},
{"learn":[4.712232782],"iteration":84,"passed_time":0.08289255756,"remaining_time":0.01462809839},
{"learn":[4.703046867],"iteration":85,"passed_time":0.08413394676,"remaining_time":0.01369622389},
{"learn":[4.698601855],"iteration":86,"passed_time":0.0848855294,"remaining_time":0.01268404462},
{"learn":[4.692429407],"iteration":87,"passed_time":0.08565877747,"remaining_time":0.01168074238},
{"learn":[4.675027364],"iteration":88,"passed_time":0.08631415809,"remaining_time":0.01066804201},
{"learn":[4.662368584],"iteration":89,"passed_time":0.0874236768,"remaining_time":0.009713741867},
{"learn":[4.646206172],"iteration":90,"passed_time":0.08814321408,"remaining_time":0.008717460733},
{"learn":[4.641245848],"iteration":91,"passed_time":0.08890136085,"remaining_time":0.007730553117},
{"learn":[4.633900435],"iteration":92,"passed_time":0.08966562228,"remaining_time":0.006749025333},
{"learn":[4.624738236],"iteration":93,"passed_time":0.09048442472,"remaining_time":0.005775601578},
{"learn":[4.612798287],"iteration":94,"passed_time":0.09112701795,"remaining_time":0.004796158839},
{"learn":[4.605222001],"iteration":95,"passed_time":0.09188874293,"remaining_time":0.003828697622},
{"learn":[4.601725912],"iteration":96,"passed_time":0.09260766501,"remaining_time":0.002864154588},
{"learn":[4.59722371],"iteration":97,"passed_time":0.09329723447,"remaining_time":0.001904025193},
{"learn":[4.580235665],"iteration":98,"passed_time":0.09392790411,"remaining_time":0.0009487667082},
{"learn":[4.57591791],"iteration":99,"passed_time":0.09466838144,"remaining_time":0}
]}